LICENSE
MANIFEST.in
README.md
setup.py
cmkpy/__init__.py
cmkpy.egg-info/PKG-INFO
cmkpy.egg-info/SOURCES.txt
cmkpy.egg-info/dependency_links.txt
cmkpy.egg-info/requires.txt
cmkpy.egg-info/top_level.txt
cmkpy/chem_data/__init__.py
cmkpy/chem_data/periodic_table.py
cmkpy/chem_struct/__init__.py
cmkpy/chem_struct/atom.py
cmkpy/chem_struct/bond.py
cmkpy/chem_struct/chem_base.py
cmkpy/chem_struct/mol.py
cmkpy/chem_struct/smiles/__init__.py
cmkpy/chem_struct/smiles/_smileslex.py
cmkpy/chem_struct/smiles/parsetab.py
cmkpy/chem_struct/smiles/smiles_lex.py
cmkpy/chem_struct/smiles/smiles_parser.py
cmkpy/chem_struct/smiles/smiles_yacc.py
cmkpy/utils_general/__init__.py
cmkpy/utils_general/cmk_assert.py
cmkpy/chem_data/__init__.py
cmkpy/chem_data/periodic_table.py
cmkpy/resource/element_name.tsv
cmkpy/resource/periodic_data.tsv