Metadata-Version: 2.1
Name: cmkpy
Version: 0.0.2
Summary: Chemical Kits for Python
Home-page: https://github.com/zbc0315/cmkpy
Author: zhang
Author-email: zhangbc0315@outlook.com
Classifier: Programming Language :: Python :: 3
Classifier: License :: OSI Approved :: MIT License
Classifier: Operating System :: OS Independent
Requires-Python: >=3.5
License-File: LICENSE
